{
  "pools": [
    {
      "rolls": 3,
      "entries": [
        {
          "type": "minecraft:item",
          "name": "minecraft:stone",
          "conditions": [
            {
              "condition": "minecraft:random_chance",
              "chance": 0.6
            }
          ]
        },
        {
          "type": "minecraft:item",
          "name": "minecraft:gunpowder",
          "functions": [
            {
              "function": "minecraft:set_count",
              "count": 1,
              "conditions": [
                {
                  "condition": "minecraft:random_chance",
                  "chance": 0.1
                }
              ]
            },
            {
              "function": "minecraft:set_count",
              "count": 2,
              "conditions": [
                {
                  "condition": "minecraft:random_chance",
                  "chance": 0.2
                }
              ]
            }
          ],
          "conditions": [
            {
              "condition": "minecraft:random_chance",
              "chance": 0.1
            }
          ]
        },
        {
          "type": "minecraft:item",
          "name": "minecraft:iron_nugget",
          "conditions": [
            {
              "condition": "minecraft:random_chance",
              "chance": 0.15
            }
          ]
        },
        {
          "type": "minecraft:item",
          "name": "minecraft:flint",
          "conditions": [
            {
              "condition": "minecraft:random_chance",
              "chance": 0.2
            }
          ]
        },
        {
          "type": "minecraft:item",
          "name": "valoria:ephemarite_low",
          "conditions": [
            {
              "condition": "minecraft:random_chance",
              "chance": 0.4
            }
          ]
        }
      ]
    }
  ]
}