{
  "type": "minecraft:archaeology",
  "pools": [
    {
      "rolls": 1,
      "entries": [
        {
          "type": "minecraft:item",
          "name": "minecraft:iron_axe",
          "weight": 1,
          "functions": [
            {
              "function": "minecraft:set_damage",
              "damage": 46,
              "conditions": [
                {
                  "condition": "minecraft:random_chance",
                  "chance": 0.65
                }
              ]
            },
            {
              "function": "minecraft:set_damage",
              "damage": 160,
              "conditions": [
                {
                  "condition": "minecraft:random_chance",
                  "chance": 0.36
                }
              ]
            }
          ]
        },
        {
          "type": "minecraft:item",
          "name": "minecraft:raw_copper",
          "weight": 5
        },
        {
          "type": "minecraft:item",
          "name": "valoria:relic_gold",
          "weight": 2
        },
        {
          "type": "minecraft:item",
          "name": "minecraft:raw_gold",
          "weight": 3
        },
        {
          "type": "minecraft:item",
          "name": "minecraft:raw_iron",
          "weight": 7
        },
        {
          "type": "minecraft:item",
          "name": "minecraft:shelter_pottery_sherd",
          "weight": 10
        },
        {
          "type": "minecraft:item",
          "name": "minecraft:miner_pottery_sherd",
          "weight": 10
        },
        {
          "type": "minecraft:item",
          "name": "minecraft:explorer_pottery_sherd",
          "weight": 15
        },
        {
          "type": "minecraft:item",
          "name": "minecraft:howl_pottery_sherd",
          "weight": 12
        },
        {
          "type": "minecraft:item",
          "name": "minecraft:copper_ingot",
          "weight": 3
        },
        {
          "type": "minecraft:item",
          "name": "minecraft:gold_ingot",
          "weight": 1
        },
        {
          "type": "minecraft:item",
          "name": "minecraft:golden_pickaxe",
          "weight": 6
        },
        {
          "type": "minecraft:item",
          "name": "minecraft:golden_chestplate",
          "weight": 3
        },
        {
          "type": "minecraft:item",
          "name": "minecraft:bone",
          "weight": 6
        },
        {
          "type": "minecraft:item",
          "name": "minecraft:gunpowder",
          "weight": 3
        },
        {
          "type": "minecraft:item",
          "name": "valoria:prospectors_pick",
          "weight": 3
        }
      ]
    }
  ]
}
